{
  "setting": {},
  "condition": {
    "plugin": {
      "list": []
    },
    "game": {
      "list": []
    },
    "gamePlugin": {
      "list": []
    },
    "miniprogram": {
      "list": [
        {
          "id": -1,
          "name": "db guide",
          "pathName": "pages/databaseGuide/databaseGuide",
          "query": ""
        },
        {
          "name": "pages/order/order",
          "pathName": "pages/order/order",
          "query": "",
          "scene": null
        },
        {
          "name": "pages/shopcar/shopcar",
          "pathName": "pages/shopcar/shopcar",
          "query": "",
          "scene": null
        },
        {
          "name": "pages/orderForm/orderForm",
          "pathName": "pages/orderForm/orderForm",
          "query": "",
          "scene": null
        },
        {
          "name": "pages/myself/myself",
          "pathName": "pages/myself/myself",
          "query": "",
          "scene": null
        },
        {
          "name": "pages/myOrderList/myOrderList",
          "pathName": "pages/myOrderList/myOrderList",
          "query": "",
          "scene": null
        }
      ]
    }
  }
}